hclogger/__init__.py
hclogger/hclogger.py
hclogger-1.0.4.dist-info/LICENSE
hclogger-1.0.4.dist-info/METADATA
hclogger-1.0.4.dist-info/WHEEL
hclogger-1.0.4.dist-info/top_level.txt
hclogger-1.0.4.dist-info/RECORD
