Metadata-Version: 2.1
Name: hclogger
Version: 1.0.4
Summary: A hierarchical and colourful logging module
Home-page: https://github.com/gaborod16/HCLogger
Author: Gabriel Amarista
Author-email: gaborod16@gmail.com
License: UNKNOWN
Platform: UNKNOWN
Classifier: Programming Language :: Python :: 3
Classifier: License :: OSI Approved :: GNU General Public License v3 (GPLv3)
Classifier: Operating System :: OS Independent
Classifier: Topic :: System :: Logging
